{
    "asset": {
        "format": "jpg",
        "id": "ea884eb0a901da5220d4abb9c9e555d6",
        "name": "00000330.jpg",
        "path": "file:D:/College/Team/Images/group_1_mayflies/ecdyonurus/00000330.jpg",
        "size": {
            "width": 480,
            "height": 360
        },
        "state": 2,
        "type": 1
    },
    "regions": [
        {
            "id": "3f2Q1tsi-",
            "type": "RECTANGLE",
            "tags": [
                "ecdyonurus"
            ],
            "boundingBox": {
                "height": 271.3490364025696,
                "width": 437.20481927710847,
                "left": 40.93373493975904,
                "top": 45.096359743040686
            },
            "points": [
                {
                    "x": 40.93373493975904,
                    "y": 45.096359743040686
                },
                {
                    "x": 478.1385542168675,
                    "y": 45.096359743040686
                },
                {
                    "x": 478.1385542168675,
                    "y": 316.4453961456103
                },
                {
                    "x": 40.93373493975904,
                    "y": 316.4453961456103
                }
            ]
        }
    ],
    "version": "2.2.0"
}