{
    "asset": {
        "format": "jpg",
        "id": "f902b3e81951ee4b000d20d99f0da066",
        "name": "00000164.jpg",
        "path": "file:D:/College/Team/Images/group_1_mayflies/ecdyonurus/00000164.jpg",
        "size": {
            "width": 900,
            "height": 600
        },
        "state": 2,
        "type": 1
    },
    "regions": [
        {
            "id": "83hXkTRI4",
            "type": "RECTANGLE",
            "tags": [
                "ecdyonurus"
            ],
            "boundingBox": {
                "height": 353.9614561027837,
                "width": 673.2334047109207,
                "left": 58.45824411134903,
                "top": 147.75160599571734
            },
            "points": [
                {
                    "x": 58.45824411134903,
                    "y": 147.75160599571734
                },
                {
                    "x": 731.6916488222697,
                    "y": 147.75160599571734
                },
                {
                    "x": 731.6916488222697,
                    "y": 501.71306209850104
                },
                {
                    "x": 58.45824411134903,
                    "y": 501.71306209850104
                }
            ]
        }
    ],
    "version": "2.2.0"
}