{
    "asset": {
        "format": "jpg",
        "id": "020079b48a2c4a94ecc79dbd5068e24b",
        "name": "00000074.jpg",
        "path": "file:D:/College/Team/CCCMI/AI_Model/images/group_1_mayflies/ephemera_danica/00000074.jpg",
        "size": {
            "width": 700,
            "height": 467
        },
        "state": 2,
        "type": 1
    },
    "regions": [
        {
            "id": "f41xDCvSa",
            "type": "RECTANGLE",
            "tags": [
                "ephemera_danica"
            ],
            "boundingBox": {
                "height": 167.5,
                "width": 583.5,
                "left": 50.75,
                "top": 146.5
            },
            "points": [
                {
                    "x": 50.75,
                    "y": 146.5
                },
                {
                    "x": 634.25,
                    "y": 146.5
                },
                {
                    "x": 634.25,
                    "y": 314
                },
                {
                    "x": 50.75,
                    "y": 314
                }
            ]
        }
    ],
    "version": "2.2.0"
}